circuitpython_typing/__init__.py
circuitpython_typing/device_drivers.py
circuitpython_typing/http.py
circuitpython_typing/io.py
circuitpython_typing/led.py
circuitpython_typing/pil.py
circuitpython_typing/pwmio.py
circuitpython_typing/py.typed
circuitpython_typing/socket.py
quax_circuitpython_typing-1.9.5.dist-info/LICENSE
quax_circuitpython_typing-1.9.5.dist-info/METADATA
quax_circuitpython_typing-1.9.5.dist-info/WHEEL
quax_circuitpython_typing-1.9.5.dist-info/top_level.txt
quax_circuitpython_typing-1.9.5.dist-info/RECORD
