Metadata-Version: 2.1
Name: quax-circuitpython-typing
Version: 1.9.5
Summary: Types needed for type annotation that are not in `typing`
Author-email: Adafruit Industries <circuitpython@adafruit.com>
License: MIT
Project-URL: Homepage, https://github.com/quaxalber/Adafruit_CircuitPython_Typing
Keywords: adafruit,blinka,circuitpython,micropython,circuitpython_typing
Classifier: Intended Audience :: Developers
Classifier: Topic :: Software Development :: Libraries
Classifier: Topic :: Software Development :: Embedded Systems
Classifier: Topic :: System :: Hardware
Classifier: License :: OSI Approved :: MIT License
Classifier: Programming Language :: Python :: 3
License-File: LICENSE
Requires-Dist: quax-Blinka
Requires-Dist: adafruit-circuitpython-busdevice
Requires-Dist: adafruit-circuitpython-requests
Requires-Dist: typing-extensions ~=4.0
Provides-Extra: optional
